<?xml version="1.0" encoding="utf-8" ?>
<dwsync>
<file name="color.js" server="187.216.141.131//var/www/mkt/" local="131401305000000000" remote="131422112400000000" />
<file name="localstorage.js" server="187.216.141.131//var/www/mkt/" local="131401305000000000" remote="131422112400000000" />
<file name="inliner.js" server="187.216.141.131//var/www/mkt/" local="131401305000000000" remote="131422112400000000" />
<file name="color.js" server="192.168.100.231//var/www/web17/" local="131401305000000000" remote="131403795600000000" />
<file name="localstorage.js" server="192.168.100.231//var/www/web17/" local="131401305000000000" remote="131403795600000000" />
<file name="inliner.js" server="192.168.100.231//var/www/web17/" local="131401305000000000" remote="131403795600000000" />
<file name="inliner.min.js" server="187.216.141.131//var/www/mkt/" local="131407433950286721" remote="131422112400000000" />
<file name="localstorage.min.js" server="187.216.141.131//var/www/mkt/" local="131407433950292551" remote="131422112400000000" />
<file name="color.min.js" server="187.216.141.131//var/www/mkt/" local="131407433950270964" remote="131422112400000000" />
</dwsync>